Metadata-Version: 1.1
Name: django-slxauth
Version: 1.11.0
Summary: Authentication provider for Solarlux Auth Service.
Home-page: https://git.solarlux.com/sl-it-dev/slx8124_django-slxauth/
Author: Enno Lohmeier
Author-email: e.lohmeier@solarlux.de
License: BSD License
Keywords: django auth account oauth
Platform: UNKNOWN
Classifier: Environment :: Web Environment
Classifier: Framework :: Django
Classifier: Framework :: Django :: 1.11
Classifier: Framework :: Django :: 2.0
Classifier: Intended Audience :: Developers
Classifier: License :: OSI Approved :: BSD License
Classifier: Operating System :: OS Independent
Classifier: Programming Language :: Python
Classifier: Programming Language :: Python :: 3
Classifier: Programming Language :: Python :: 3.4
Classifier: Programming Language :: Python :: 3.5
Classifier: Programming Language :: Python :: 3.6
Classifier: Topic :: Internet :: WWW/HTTP
Classifier: Topic :: Internet :: WWW/HTTP :: Dynamic Content
